LICENSE
NOTICE
README.md
setup.cfg
setup.py
coppertop/dm/_irange.py
coppertop/dm/_range.py
coppertop/dm/canvas.py
coppertop/dm/distributions.py
coppertop/dm/flux.py
coppertop/dm/fs.py
coppertop/dm/numpy.py
coppertop/dm/ols.py
coppertop/dm/p9.py
coppertop/dm/pandaframe.py
coppertop/dm/plotting.py
coppertop/dm/pmf.py
coppertop/dm/polarframe.py
coppertop/dm/pp.py
coppertop/dm/rates.py
coppertop/dm/repl.py
coppertop/dm/sequences.py
coppertop/dm/testing.py
coppertop/dm/wip.py
coppertop/dm/_core/structs.py
coppertop/dm/_core/types.py
coppertop/dm/core/__init__.py
coppertop/dm/core/aggman.py
coppertop/dm/core/bones.py
coppertop/dm/core/bones2.py
coppertop/dm/core/comparisons.py
coppertop/dm/core/contextual_scope.py
coppertop/dm/core/conv.py
coppertop/dm/core/datetime.py
coppertop/dm/core/frame.py
coppertop/dm/core/maths.py
coppertop/dm/core/misc.py
coppertop/dm/core/stats.py
coppertop/dm/core/structs.py
coppertop/dm/core/text.py
coppertop/dm/core/types.py
coppertop/dm/core/unicode.py
coppertop/dm/finance/types.py
coppertop/dm/frame/csv.py
coppertop/dm/linalg/core.py
coppertop/dm/linalg/orient.py
coppertop/dm/linalg/types.py
coppertop/dm/linalg/algos/underdetermined.py
coppertop/dm/stdlib/__init__.py
coppertop/dm/stdlib/core.py
coppertop/dm/stdlib/ops.py
coppertop/dm/utils/countlines.py
coppertop/dm/utils/testing.py
coppertop_bones_libs.egg-info/PKG-INFO
coppertop_bones_libs.egg-info/SOURCES.txt
coppertop_bones_libs.egg-info/dependency_links.txt
coppertop_bones_libs.egg-info/not-zip-safe
coppertop_bones_libs.egg-info/requires.txt
coppertop_bones_libs.egg-info/top_level.txt