Metadata-Version: 2.4
Name: coppertop-bones-libs
Version: 2025.6.8
Summary: The dm and penfold standard libraries for coppertop and bones
Home-page: https://github.com/coppertop-bones/coppertop-libs
Download-URL: 
Author: David Briant
Author-email: dangermouseb@forwarding.cc
License: OSI Approved :: Apache Software License
Keywords: multiple,dispatch,piping,pipeline,pipe,functional,multimethods,multidispatch,functools,lambda,curry,currying,dataframe,polars,pandas
Classifier: Development Status :: 3 - Alpha
Classifier: Intended Audience :: Developers
Classifier: Intended Audience :: End Users/Desktop
Classifier: Intended Audience :: Science/Research
Classifier: Topic :: Utilities
Classifier: License :: OSI Approved :: Apache Software License
Classifier: Programming Language :: Python :: 3.11
Requires-Python: >=3.11
License-File: LICENSE
License-File: NOTICE
Requires-Dist: coppertop-bones==2025.6.8
Dynamic: author
Dynamic: author-email
Dynamic: classifier
Dynamic: description
Dynamic: description-content-type
Dynamic: home-page
Dynamic: keywords
Dynamic: license
Dynamic: license-file
Dynamic: requires-dist
Dynamic: requires-python
Dynamic: summary
